cam_utils/__init__.py
cam_utils/api_request.py
cam_utils/db_elasticsearch.py
cam_utils/db_ldap.py
cam_utils/db_mysql.py
cam_utils/db_rabbitmq.py
cam_utils/valida_info.py
cam_utils/acsclient/__init__.py
cam_utils/acsclient/acsclient.py
cam_utils/acsclient/templates/device.j2
cam_utils/acsclient/templates/devicegroup.j2
cam_utils/acsclient/templates/radius_device.j2
cam_utils/acsclient/templates/search.j2
cam_utils/asterisk/__init__.py
cam_utils/asterisk/actions.py
cam_utils/asterisk/ami.py
cam_utils/asterisk/exceptions.py
cam_utils-0.2.8.dist-info/METADATA
cam_utils-0.2.8.dist-info/WHEEL
cam_utils-0.2.8.dist-info/licenses/LICENSE
cam_utils-0.2.8.dist-info/RECORD
