Metadata-Version: 2.3
Name: cam_utils
Version: 0.2.8
Summary: CAM UTILS LIBRARY TO PYTHON PROJECTS
Project-URL: Homepage, https://repo.camvoip.com.br/engenharia/bibliotecas-cam/python/cam_utils
Project-URL: Issues, https://repo.camvoip.com.br/engenharia/bibliotecas-cam/python/cam_utils/-/issues
Author-email: CAM TECNOLOGIA LTDA ME <atendimento@camtecnologia.com.br>
License-File: LICENSE
Classifier: License :: OSI Approved :: MIT License
Classifier: Operating System :: POSIX :: Linux
Classifier: Programming Language :: Python :: 3
Requires-Python: >=3.8
